aactivator.py
aactivator-2.0.0.dist-info/LICENSE
aactivator-2.0.0.dist-info/METADATA
aactivator-2.0.0.dist-info/WHEEL
aactivator-2.0.0.dist-info/entry_points.txt
aactivator-2.0.0.dist-info/top_level.txt
aactivator-2.0.0.dist-info/RECORD
