Metadata-Version: 2.1
Name: aactivator
Version: 2.0.0
Summary: Automatically activate Python virtualenvs (and other environments).
Home-page: https://github.com/Yelp/aactivator
Author: Yelp
License: UNKNOWN
Platform: linux
Classifier: License :: OSI Approved :: MIT License
Classifier: Programming Language :: Python :: 3
Classifier: Programming Language :: Python :: 3.4
Classifier: Programming Language :: Python :: 3.5
Classifier: Programming Language :: Python :: 3.6
Requires-Python: >=3.3
License-File: LICENSE
